<?xml version="1.0" encoding="UTF-8" standalone="yes"?>
<LN>
    <name>SVTR</name>
    <description>SVTR Model</description>
    <classType>SVTR</classType>
    <layoutX>-1.0</layoutX>
    <layoutY>-1.0</layoutY>
    <dataSetInput>
        <name>InputDS</name>
        <description>DataSet for input connections</description>
        <type>Node</type>
        <intgPd>0</intgPd>
        <bufTime>0</bufTime>
        <layoutX>-1.0</layoutX>
        <layoutY>-1.0</layoutY>
        <cppType>ExtU_SVTRADVANCED_T</cppType>
        <cppName>SVTRADVANCED_U</cppName>
        <DO>
            <dataObjectName>iec_WYE</dataObjectName>
            <dataAttributeName>in_PhV1</dataAttributeName>
            <DO>
                <dataObjectName>iec_CMV</dataObjectName>
                <dataAttributeName>phsA</dataAttributeName>
                <DO>
                    <dataObjectName>iec_Vector</dataObjectName>
                    <dataAttributeName>cVal</dataAttributeName>
                    <DO>
                        <dataObjectName>float</dataObjectName>
                        <dataAttributeName>mag</dataAttributeName>
                        <value>0.0</value>
                    </DO>
                    <DO>
                        <dataObjectName>float</dataObjectName>
                        <dataAttributeName>ang</dataAttributeName>
                        <value>0.0</value>
                    </DO>
                </DO>
                <DO>
                    <dataObjectName>iec_Quality</dataObjectName>
                    <dataAttributeName>q</dataAttributeName>
                    <DO>
                        <dataObjectName>unsigned char</dataObjectName>
                        <dataAttributeName>validity</dataAttributeName>
                        <value>0</value>
                    </DO>
                </DO>
            </DO>
            <DO>
                <dataObjectName>iec_CMV</dataObjectName>
                <dataAttributeName>phsB</dataAttributeName>
                <DO>
                    <dataObjectName>iec_Vector</dataObjectName>
                    <dataAttributeName>cVal</dataAttributeName>
                    <DO>
                        <dataObjectName>float</dataObjectName>
                        <dataAttributeName>mag</dataAttributeName>
                        <value>0.0</value>
                    </DO>
                    <DO>
                        <dataObjectName>float</dataObjectName>
                        <dataAttributeName>ang</dataAttributeName>
                        <value>0.0</value>
                    </DO>
                </DO>
                <DO>
                    <dataObjectName>iec_Quality</dataObjectName>
                    <dataAttributeName>q</dataAttributeName>
                    <DO>
                        <dataObjectName>unsigned char</dataObjectName>
                        <dataAttributeName>validity</dataAttributeName>
                        <value>0</value>
                    </DO>
                </DO>
            </DO>
            <DO>
                <dataObjectName>iec_CMV</dataObjectName>
                <dataAttributeName>phsC</dataAttributeName>
                <DO>
                    <dataObjectName>iec_Vector</dataObjectName>
                    <dataAttributeName>cVal</dataAttributeName>
                    <DO>
                        <dataObjectName>float</dataObjectName>
                        <dataAttributeName>mag</dataAttributeName>
                        <value>0.0</value>
                    </DO>
                    <DO>
                        <dataObjectName>float</dataObjectName>
                        <dataAttributeName>ang</dataAttributeName>
                        <value>0.0</value>
                    </DO>
                </DO>
                <DO>
                    <dataObjectName>iec_Quality</dataObjectName>
                    <dataAttributeName>q</dataAttributeName>
                    <DO>
                        <dataObjectName>unsigned char</dataObjectName>
                        <dataAttributeName>validity</dataAttributeName>
                        <value>0</value>
                    </DO>
                </DO>
            </DO>
            <DO>
                <dataObjectName>iec_CMV</dataObjectName>
                <dataAttributeName>neut</dataAttributeName>
                <DO>
                    <dataObjectName>iec_Vector</dataObjectName>
                    <dataAttributeName>cVal</dataAttributeName>
                    <DO>
                        <dataObjectName>float</dataObjectName>
                        <dataAttributeName>mag</dataAttributeName>
                        <value>0.0</value>
                    </DO>
                    <DO>
                        <dataObjectName>float</dataObjectName>
                        <dataAttributeName>ang</dataAttributeName>
                        <value>0.0</value>
                    </DO>
                </DO>
                <DO>
                    <dataObjectName>iec_Quality</dataObjectName>
                    <dataAttributeName>q</dataAttributeName>
                    <DO>
                        <dataObjectName>unsigned char</dataObjectName>
                        <dataAttributeName>validity</dataAttributeName>
                        <value>0</value>
                    </DO>
                </DO>
            </DO>
        </DO>
        <DO>
            <dataObjectName>iec_WYE</dataObjectName>
            <dataAttributeName>in_PhV2</dataAttributeName>
            <DO>
                <dataObjectName>iec_CMV</dataObjectName>
                <dataAttributeName>phsA</dataAttributeName>
                <DO>
                    <dataObjectName>iec_Vector</dataObjectName>
                    <dataAttributeName>cVal</dataAttributeName>
                    <DO>
                        <dataObjectName>float</dataObjectName>
                        <dataAttributeName>mag</dataAttributeName>
                        <value>0.0</value>
                    </DO>
                    <DO>
                        <dataObjectName>float</dataObjectName>
                        <dataAttributeName>ang</dataAttributeName>
                        <value>0.0</value>
                    </DO>
                </DO>
                <DO>
                    <dataObjectName>iec_Quality</dataObjectName>
                    <dataAttributeName>q</dataAttributeName>
                    <DO>
                        <dataObjectName>unsigned char</dataObjectName>
                        <dataAttributeName>validity</dataAttributeName>
                        <value>0</value>
                    </DO>
                </DO>
            </DO>
            <DO>
                <dataObjectName>iec_CMV</dataObjectName>
                <dataAttributeName>phsB</dataAttributeName>
                <DO>
                    <dataObjectName>iec_Vector</dataObjectName>
                    <dataAttributeName>cVal</dataAttributeName>
                    <DO>
                        <dataObjectName>float</dataObjectName>
                        <dataAttributeName>mag</dataAttributeName>
                        <value>0.0</value>
                    </DO>
                    <DO>
                        <dataObjectName>float</dataObjectName>
                        <dataAttributeName>ang</dataAttributeName>
                        <value>0.0</value>
                    </DO>
                </DO>
                <DO>
                    <dataObjectName>iec_Quality</dataObjectName>
                    <dataAttributeName>q</dataAttributeName>
                    <DO>
                        <dataObjectName>unsigned char</dataObjectName>
                        <dataAttributeName>validity</dataAttributeName>
                        <value>0</value>
                    </DO>
                </DO>
            </DO>
            <DO>
                <dataObjectName>iec_CMV</dataObjectName>
                <dataAttributeName>phsC</dataAttributeName>
                <DO>
                    <dataObjectName>iec_Vector</dataObjectName>
                    <dataAttributeName>cVal</dataAttributeName>
                    <DO>
                        <dataObjectName>float</dataObjectName>
                        <dataAttributeName>mag</dataAttributeName>
                        <value>0.0</value>
                    </DO>
                    <DO>
                        <dataObjectName>float</dataObjectName>
                        <dataAttributeName>ang</dataAttributeName>
                        <value>0.0</value>
                    </DO>
                </DO>
                <DO>
                    <dataObjectName>iec_Quality</dataObjectName>
                    <dataAttributeName>q</dataAttributeName>
                    <DO>
                        <dataObjectName>unsigned char</dataObjectName>
                        <dataAttributeName>validity</dataAttributeName>
                        <value>0</value>
                    </DO>
                </DO>
            </DO>
            <DO>
                <dataObjectName>iec_CMV</dataObjectName>
                <dataAttributeName>neut</dataAttributeName>
                <DO>
                    <dataObjectName>iec_Vector</dataObjectName>
                    <dataAttributeName>cVal</dataAttributeName>
                    <DO>
                        <dataObjectName>float</dataObjectName>
                        <dataAttributeName>mag</dataAttributeName>
                        <value>0.0</value>
                    </DO>
                    <DO>
                        <dataObjectName>float</dataObjectName>
                        <dataAttributeName>ang</dataAttributeName>
                        <value>0.0</value>
                    </DO>
                </DO>
                <DO>
                    <dataObjectName>iec_Quality</dataObjectName>
                    <dataAttributeName>q</dataAttributeName>
                    <DO>
                        <dataObjectName>unsigned char</dataObjectName>
                        <dataAttributeName>validity</dataAttributeName>
                        <value>0</value>
                    </DO>
                </DO>
            </DO>
        </DO>
        <DO>
            <dataObjectName>iec_WYE</dataObjectName>
            <dataAttributeName>in_A</dataAttributeName>
            <DO>
                <dataObjectName>iec_CMV</dataObjectName>
                <dataAttributeName>phsA</dataAttributeName>
                <DO>
                    <dataObjectName>iec_Vector</dataObjectName>
                    <dataAttributeName>cVal</dataAttributeName>
                    <DO>
                        <dataObjectName>float</dataObjectName>
                        <dataAttributeName>mag</dataAttributeName>
                        <value>0.0</value>
                    </DO>
                    <DO>
                        <dataObjectName>float</dataObjectName>
                        <dataAttributeName>ang</dataAttributeName>
                        <value>0.0</value>
                    </DO>
                </DO>
                <DO>
                    <dataObjectName>iec_Quality</dataObjectName>
                    <dataAttributeName>q</dataAttributeName>
                    <DO>
                        <dataObjectName>unsigned char</dataObjectName>
                        <dataAttributeName>validity</dataAttributeName>
                        <value>0</value>
                    </DO>
                </DO>
            </DO>
            <DO>
                <dataObjectName>iec_CMV</dataObjectName>
                <dataAttributeName>phsB</dataAttributeName>
                <DO>
                    <dataObjectName>iec_Vector</dataObjectName>
                    <dataAttributeName>cVal</dataAttributeName>
                    <DO>
                        <dataObjectName>float</dataObjectName>
                        <dataAttributeName>mag</dataAttributeName>
                        <value>0.0</value>
                    </DO>
                    <DO>
                        <dataObjectName>float</dataObjectName>
                        <dataAttributeName>ang</dataAttributeName>
                        <value>0.0</value>
                    </DO>
                </DO>
                <DO>
                    <dataObjectName>iec_Quality</dataObjectName>
                    <dataAttributeName>q</dataAttributeName>
                    <DO>
                        <dataObjectName>unsigned char</dataObjectName>
                        <dataAttributeName>validity</dataAttributeName>
                        <value>0</value>
                    </DO>
                </DO>
            </DO>
            <DO>
                <dataObjectName>iec_CMV</dataObjectName>
                <dataAttributeName>phsC</dataAttributeName>
                <DO>
                    <dataObjectName>iec_Vector</dataObjectName>
                    <dataAttributeName>cVal</dataAttributeName>
                    <DO>
                        <dataObjectName>float</dataObjectName>
                        <dataAttributeName>mag</dataAttributeName>
                        <value>0.0</value>
                    </DO>
                    <DO>
                        <dataObjectName>float</dataObjectName>
                        <dataAttributeName>ang</dataAttributeName>
                        <value>0.0</value>
                    </DO>
                </DO>
                <DO>
                    <dataObjectName>iec_Quality</dataObjectName>
                    <dataAttributeName>q</dataAttributeName>
                    <DO>
                        <dataObjectName>unsigned char</dataObjectName>
                        <dataAttributeName>validity</dataAttributeName>
                        <value>0</value>
                    </DO>
                </DO>
            </DO>
            <DO>
                <dataObjectName>iec_CMV</dataObjectName>
                <dataAttributeName>neut</dataAttributeName>
                <DO>
                    <dataObjectName>iec_Vector</dataObjectName>
                    <dataAttributeName>cVal</dataAttributeName>
                    <DO>
                        <dataObjectName>float</dataObjectName>
                        <dataAttributeName>mag</dataAttributeName>
                        <value>0.0</value>
                    </DO>
                    <DO>
                        <dataObjectName>float</dataObjectName>
                        <dataAttributeName>ang</dataAttributeName>
                        <value>0.0</value>
                    </DO>
                </DO>
                <DO>
                    <dataObjectName>iec_Quality</dataObjectName>
                    <dataAttributeName>q</dataAttributeName>
                    <DO>
                        <dataObjectName>unsigned char</dataObjectName>
                        <dataAttributeName>validity</dataAttributeName>
                        <value>0</value>
                    </DO>
                </DO>
            </DO>
        </DO>
        <DO>
            <dataObjectName>iec_SEQ</dataObjectName>
            <dataAttributeName>in_SeqV</dataAttributeName>
            <DO>
                <dataObjectName>iec_CMV</dataObjectName>
                <dataAttributeName>c1</dataAttributeName>
                <DO>
                    <dataObjectName>iec_Vector</dataObjectName>
                    <dataAttributeName>cVal</dataAttributeName>
                    <DO>
                        <dataObjectName>float</dataObjectName>
                        <dataAttributeName>mag</dataAttributeName>
                        <value>0.0</value>
                    </DO>
                    <DO>
                        <dataObjectName>float</dataObjectName>
                        <dataAttributeName>ang</dataAttributeName>
                        <value>0.0</value>
                    </DO>
                </DO>
                <DO>
                    <dataObjectName>iec_Quality</dataObjectName>
                    <dataAttributeName>q</dataAttributeName>
                    <DO>
                        <dataObjectName>unsigned char</dataObjectName>
                        <dataAttributeName>validity</dataAttributeName>
                        <value>0</value>
                    </DO>
                </DO>
            </DO>
            <DO>
                <dataObjectName>iec_CMV</dataObjectName>
                <dataAttributeName>c2</dataAttributeName>
                <DO>
                    <dataObjectName>iec_Vector</dataObjectName>
                    <dataAttributeName>cVal</dataAttributeName>
                    <DO>
                        <dataObjectName>float</dataObjectName>
                        <dataAttributeName>mag</dataAttributeName>
                        <value>0.0</value>
                    </DO>
                    <DO>
                        <dataObjectName>float</dataObjectName>
                        <dataAttributeName>ang</dataAttributeName>
                        <value>0.0</value>
                    </DO>
                </DO>
                <DO>
                    <dataObjectName>iec_Quality</dataObjectName>
                    <dataAttributeName>q</dataAttributeName>
                    <DO>
                        <dataObjectName>unsigned char</dataObjectName>
                        <dataAttributeName>validity</dataAttributeName>
                        <value>0</value>
                    </DO>
                </DO>
            </DO>
            <DO>
                <dataObjectName>iec_CMV</dataObjectName>
                <dataAttributeName>c3</dataAttributeName>
                <DO>
                    <dataObjectName>iec_Vector</dataObjectName>
                    <dataAttributeName>cVal</dataAttributeName>
                    <DO>
                        <dataObjectName>float</dataObjectName>
                        <dataAttributeName>mag</dataAttributeName>
                        <value>0.0</value>
                    </DO>
                    <DO>
                        <dataObjectName>float</dataObjectName>
                        <dataAttributeName>ang</dataAttributeName>
                        <value>0.0</value>
                    </DO>
                </DO>
                <DO>
                    <dataObjectName>iec_Quality</dataObjectName>
                    <dataAttributeName>q</dataAttributeName>
                    <DO>
                        <dataObjectName>unsigned char</dataObjectName>
                        <dataAttributeName>validity</dataAttributeName>
                        <value>0</value>
                    </DO>
                </DO>
            </DO>
        </DO>
        <DO>
            <dataObjectName>iec_SEQ</dataObjectName>
            <dataAttributeName>in_SeqA</dataAttributeName>
            <DO>
                <dataObjectName>iec_CMV</dataObjectName>
                <dataAttributeName>c1</dataAttributeName>
                <DO>
                    <dataObjectName>iec_Vector</dataObjectName>
                    <dataAttributeName>cVal</dataAttributeName>
                    <DO>
                        <dataObjectName>float</dataObjectName>
                        <dataAttributeName>mag</dataAttributeName>
                        <value>0.0</value>
                    </DO>
                    <DO>
                        <dataObjectName>float</dataObjectName>
                        <dataAttributeName>ang</dataAttributeName>
                        <value>0.0</value>
                    </DO>
                </DO>
                <DO>
                    <dataObjectName>iec_Quality</dataObjectName>
                    <dataAttributeName>q</dataAttributeName>
                    <DO>
                        <dataObjectName>unsigned char</dataObjectName>
                        <dataAttributeName>validity</dataAttributeName>
                        <value>0</value>
                    </DO>
                </DO>
            </DO>
            <DO>
                <dataObjectName>iec_CMV</dataObjectName>
                <dataAttributeName>c2</dataAttributeName>
                <DO>
                    <dataObjectName>iec_Vector</dataObjectName>
                    <dataAttributeName>cVal</dataAttributeName>
                    <DO>
                        <dataObjectName>float</dataObjectName>
                        <dataAttributeName>mag</dataAttributeName>
                        <value>0.0</value>
                    </DO>
                    <DO>
                        <dataObjectName>float</dataObjectName>
                        <dataAttributeName>ang</dataAttributeName>
                        <value>0.0</value>
                    </DO>
                </DO>
                <DO>
                    <dataObjectName>iec_Quality</dataObjectName>
                    <dataAttributeName>q</dataAttributeName>
                    <DO>
                        <dataObjectName>unsigned char</dataObjectName>
                        <dataAttributeName>validity</dataAttributeName>
                        <value>0</value>
                    </DO>
                </DO>
            </DO>
            <DO>
                <dataObjectName>iec_CMV</dataObjectName>
                <dataAttributeName>c3</dataAttributeName>
                <DO>
                    <dataObjectName>iec_Vector</dataObjectName>
                    <dataAttributeName>cVal</dataAttributeName>
                    <DO>
                        <dataObjectName>float</dataObjectName>
                        <dataAttributeName>mag</dataAttributeName>
                        <value>0.0</value>
                    </DO>
                    <DO>
                        <dataObjectName>float</dataObjectName>
                        <dataAttributeName>ang</dataAttributeName>
                        <value>0.0</value>
                    </DO>
                </DO>
                <DO>
                    <dataObjectName>iec_Quality</dataObjectName>
                    <dataAttributeName>q</dataAttributeName>
                    <DO>
                        <dataObjectName>unsigned char</dataObjectName>
                        <dataAttributeName>validity</dataAttributeName>
                        <value>0</value>
                    </DO>
                </DO>
            </DO>
        </DO>
        <DO>
            <dataObjectName>iec_SPS</dataObjectName>
            <dataAttributeName>in_Pos</dataAttributeName>
            <DO>
                <dataObjectName>unsigned char</dataObjectName>
                <dataAttributeName>stVal</dataAttributeName>
                <value>0</value>
            </DO>
            <DO>
                <dataObjectName>iec_Quality</dataObjectName>
                <dataAttributeName>q</dataAttributeName>
                <DO>
                    <dataObjectName>unsigned char</dataObjectName>
                    <dataAttributeName>validity</dataAttributeName>
                    <value>0</value>
                </DO>
            </DO>
        </DO>
        <DO>
            <dataObjectName>unsigned char</dataObjectName>
            <dataAttributeName>set_Mod</dataAttributeName>
            <value>0</value>
        </DO>
        <DO>
            <dataObjectName>unsigned char</dataObjectName>
            <dataAttributeName>set_SeqMod</dataAttributeName>
            <value>0</value>
        </DO>
        <DO>
            <dataObjectName>unsigned char</dataObjectName>
            <dataAttributeName>set_CBMod</dataAttributeName>
            <value>0</value>
        </DO>
        <DO>
            <dataObjectName>float</dataObjectName>
            <dataAttributeName>set_StrValVImb</dataAttributeName>
            <value>0.0</value>
        </DO>
        <DO>
            <dataObjectName>float</dataObjectName>
            <dataAttributeName>set_RatA</dataAttributeName>
            <value>0.0</value>
        </DO>
        <DO>
            <dataObjectName>float</dataObjectName>
            <dataAttributeName>set_RatB</dataAttributeName>
            <value>0.0</value>
        </DO>
        <DO>
            <dataObjectName>float</dataObjectName>
            <dataAttributeName>set_RatC</dataAttributeName>
            <value>0.0</value>
        </DO>
        <DO>
            <dataObjectName>float</dataObjectName>
            <dataAttributeName>set_Rat0</dataAttributeName>
            <value>0.0</value>
        </DO>
        <DO>
            <dataObjectName>float</dataObjectName>
            <dataAttributeName>set_RatA1</dataAttributeName>
            <value>0.0</value>
        </DO>
        <DO>
            <dataObjectName>float</dataObjectName>
            <dataAttributeName>set_StrValAMin</dataAttributeName>
            <value>0.0</value>
        </DO>
        <DO>
            <dataObjectName>float</dataObjectName>
            <dataAttributeName>set_StrValVMin</dataAttributeName>
            <value>0.0</value>
        </DO>
        <DO>
            <dataObjectName>float</dataObjectName>
            <dataAttributeName>set_StrValNgSeqA</dataAttributeName>
            <value>0.0</value>
        </DO>
        <DO>
            <dataObjectName>float</dataObjectName>
            <dataAttributeName>set_StrValNgSeqV</dataAttributeName>
            <value>0.0</value>
        </DO>
        <DO>
            <dataObjectName>float</dataObjectName>
            <dataAttributeName>set_StrValZerSeqA</dataAttributeName>
            <value>0.0</value>
        </DO>
        <DO>
            <dataObjectName>float</dataObjectName>
            <dataAttributeName>set_StrValZerSeqV</dataAttributeName>
            <value>0.0</value>
        </DO>
    </dataSetInput>
    <dataSetOutput>
        <name>OutputDS</name>
        <description>DataSet for output connections</description>
        <type>Node</type>
        <intgPd>0</intgPd>
        <bufTime>0</bufTime>
        <layoutX>-1.0</layoutX>
        <layoutY>-1.0</layoutY>
        <cppType>ExtY_SVTRADVANCED_T</cppType>
        <cppName>SVTRADVANCED_Y</cppName>
        <DO>
            <dataObjectName>iec_SPS</dataObjectName>
            <dataAttributeName>out_BlkV</dataAttributeName>
            <DO>
                <dataObjectName>unsigned char</dataObjectName>
                <dataAttributeName>stVal</dataAttributeName>
                <value>0</value>
            </DO>
            <DO>
                <dataObjectName>iec_Quality</dataObjectName>
                <dataAttributeName>q</dataAttributeName>
                <DO>
                    <dataObjectName>unsigned char</dataObjectName>
                    <dataAttributeName>validity</dataAttributeName>
                    <value>0</value>
                </DO>
            </DO>
        </DO>
    </dataSetOutput>
</LN>
